{"data":[{"type":{"id":"abtest","version":"1.0.0"},"id":"ab-start-my-cart","group":false,"path":"/objects/abtest/1.0.0/ab-start-my-cart"},{"type":{"id":"abtest","version":"1.0.0"},"id":"abn","group":false,"path":"/objects/abtest/1.0.0/abn"},{"type":{"id":"abtest","version":"1.0.0"},"id":"abtest-2","group":false,"path":"/objects/abtest/1.0.0/abtest-2"},{"type":{"id":"abtest","version":"1.0.0"},"id":"amp-abtest","group":false,"path":"/objects/abtest/1.0.0/amp-abtest"},{"type":{"id":"abtest","version":"1.0.0"},"id":"anything","group":false,"path":"/objects/abtest/1.0.0/anything"},{"type":{"id":"abtest","version":"1.0.0"},"id":"buyitagain","group":false,"path":"/objects/abtest/1.0.0/buyitagain"},{"type":{"id":"abtest","version":"1.0.0"},"id":"cartsubtotal","group":false,"path":"/objects/abtest/1.0.0/cartsubtotal"},{"type":{"id":"abtest","version":"1.0.0"},"id":"control","group":false,"path":"/objects/abtest/1.0.0/control"},{"type":{"id":"abtest","version":"1.0.0"},"id":"coupontoggle","group":false,"path":"/objects/abtest/1.0.0/coupontoggle"},{"type":{"id":"abtest","version":"1.0.0"},"id":"department/dcptools-2777-abtest","group":false,"path":"/objects/abtest/1.0.0/department/dcptools-2777-abtest"},{"type":{"id":"abtest","version":"1.0.0"},"id":"deptnamingbeverage","group":false,"path":"/objects/abtest/1.0.0/deptnamingbeverage"},{"type":{"id":"abtest","version":"1.0.0"},"id":"deptnaminggrocery","group":false,"path":"/objects/abtest/1.0.0/deptnaminggrocery"},{"type":{"id":"abtest","version":"1.0.0"},"id":"deptnaminghousewares","group":false,"path":"/objects/abtest/1.0.0/deptnaminghousewares"},{"type":{"id":"abtest","version":"1.0.0"},"id":"deptnamingliquor","group":false,"path":"/objects/abtest/1.0.0/deptnamingliquor"},{"type":{"id":"abtest","version":"1.0.0"},"id":"featuredvssponsored","group":false,"path":"/objects/abtest/1.0.0/featuredvssponsored"},{"type":{"id":"abtest","version":"1.0.0"},"id":"fvss","group":false,"path":"/objects/abtest/1.0.0/fvss"},{"type":{"id":"abtest","version":"1.0.0"},"id":"gary-test","group":false,"path":"/objects/abtest/1.0.0/gary-test"},{"type":{"id":"abtest","version":"1.0.0"},"id":"hidebenefits","group":false,"path":"/objects/abtest/1.0.0/hidebenefits"},{"type":{"id":"abtest","version":"1.0.0"},"id":"hidebenefits_others","group":false,"path":"/objects/abtest/1.0.0/hidebenefits_others"},{"type":{"id":"abtest","version":"1.0.0"},"id":"homegrown","group":false,"path":"/objects/abtest/1.0.0/homegrown"}],"meta":{"totalPages":2,"totalCount":34}}
